CREDITS.txt
LICENSE.txt
README.txt
VERSION.txt
benchmark.py
cypsrc
setup.py
tests.py
docs/reading-data.txt
docs/data/test_uk.dbf
docs/data/test_uk.shp
docs/data/test_uk.shx
src/WorldMill.egg-info/PKG-INFO
src/WorldMill.egg-info/SOURCES.txt
src/WorldMill.egg-info/dependency_links.txt
src/WorldMill.egg-info/requires.txt
src/WorldMill.egg-info/top_level.txt
src/mill/__init__.py
src/mill/collection.c
src/mill/collection.pyx
src/mill/feature.py
src/mill/ograpi.pxd
src/mill/ogrinit.c
src/mill/ogrinit.pyx
src/mill/workspace.c
src/mill/workspace.pyx
