Metadata-Version: 1.0
Name: WorldMill
Version: 0.1
Summary: Access and transform geospatial feature data
Home-page: http://trac.gispython.org/projects/PCL/wiki/WorldMill
Author: Sean Gillies
Author-email: sgillies@frii.com
License: BSD
Keywords: gis vector feature data
Platform: UNKNOWN
Classifier: Development Status :: 3 - Alpha
Classifier: Intended Audience :: Developers
Classifier: Intended Audience :: Science/Research
Classifier: License :: OSI Approved :: BSD License
Classifier: Operating System :: OS Independent
Classifier: Programming Language :: Python
Classifier: Topic :: Scientific/Engineering :: GIS
